nphiesify/__init__.py
nphiesify/codesystems/__init__.py
nphiesify/codesystems/codeableconcepts.py
nphiesify/codesystems/codesets.py
nphiesify/datatypes/__init__.py
nphiesify/datatypes/basetypes.py
nphiesify/datatypes/complextypes.py
nphiesify/datatypes/primitivetypes.py
nphiesify/resources/__init__.py
nphiesify/resources/resources.py
nphiesify/resources/base/__init__.py
nphiesify/resources/base/individuals.py
nphiesify/resources/clinical/__init__.py
nphiesify/resources/clinical/careprovision.py
nphiesify/resources/financial/__init__.py
nphiesify/resources/financial/billing.py
nphiesify/resources/financial/support.py
nphiesify/resources/foundation/__init__.py
nphiesify/resources/foundation/other.py
nphiesify-0.0.2.dist-info/licenses/LICENSE
nphiesify-0.0.2.dist-info/METADATA
nphiesify-0.0.2.dist-info/WHEEL
nphiesify-0.0.2.dist-info/top_level.txt
nphiesify-0.0.2.dist-info/RECORD
